{"data":[{"timeEst":743135280,"transitStation":true,"stationId":"DU","stationName":"DURI"},{"stationId":"GGL","stationName":"GROGOL","timeEst":743135460,"transitStation":false},{"stationId":"PSG","stationName":"PESING","transitStation":false,"timeEst":743135580},{"timeEst":743135700,"stationName":"TAMANKOTA","transitStation":false,"stationId":"TKO"},{"stationName":"BOJONGINDAH","stationId":"BOI","timeEst":743135820,"transitStation":false},{"stationName":"RAWABUAYA","transitStation":false,"timeEst":743136060,"stationId":"RW"},{"stationId":"KDS","timeEst":743136240,"transitStation":false,"stationName":"KALIDERES"},{"stationName":"PORIS","stationId":"PI","timeEst":743136420,"transitStation":false},{"stationId":"BPR","timeEst":743136600,"transitStation":false,"stationName":"BATUCEPER"},{"timeEst":743136780,"stationId":"TTI","stationName":"TANAHTINGGI","transitStation":false},{"stationName":"TANGERANG","stationId":"TNG","transitStation":false,"timeEst":743136960}]}