{"data":[{"timeEst":743151660,"transitStation":true,"stationId":"KPB","stationName":"KAMPUNGBANDAN"},{"stationId":"AK","stationName":"ANGKE","timeEst":743152200,"transitStation":false},{"stationId":"DU","stationName":"DURI","transitStation":true,"timeEst":743152440},{"stationId":"THB","transitStation":true,"stationName":"TANAHABANG","timeEst":743152920},{"timeEst":743153100,"stationName":"KARET","transitStation":false,"stationId":"KAT"},{"stationId":"SUDB","timeEst":743153160,"transitStation":false,"stationName":"SUDIRMANBARU"},{"stationName":"SUDIRMAN","stationId":"SUD","timeEst":743153220,"transitStation":false},{"stationName":"MANGGARAI","transitStation":true,"timeEst":743153640,"stationId":"MRI"},{"stationId":"MTR","transitStation":false,"timeEst":743153760,"stationName":"MATRAMAN"},{"stationName":"JATINEGARA","stationId":"JNG","timeEst":743154120,"transitStation":true},{"stationId":"KLD","timeEst":743154300,"transitStation":false,"stationName":"KLENDER"},{"timeEst":743154420,"stationId":"BUA","stationName":"BUARAN","transitStation":false},{"stationId":"KLDB","timeEst":743154480,"stationName":"KLENDERBARU","transitStation":false},{"stationId":"CUK","stationName":"CAKUNG","timeEst":743154960,"transitStation":false},{"stationId":"KRI","stationName":"KRANJI","timeEst":743155140,"transitStation":false},{"timeEst":743155440,"stationId":"BKS","stationName":"BEKASI","transitStation":false},{"stationId":"BKST","transitStation":false,"timeEst":743155560,"stationName":"BEKASITIMUR"},{"stationName":"TAMBUN","transitStation":false,"stationId":"TB","timeEst":743155980},{"stationName":"CIBITUNG","stationId":"CIT","timeEst":743156160,"transitStation":false},{"stationName":"M.TELAGAMURNI","transitStation":false,"timeEst":743156280,"stationId":"TLM"},{"transitStation":false,"stationName":"CIKARANG","timeEst":743156640,"stationId":"CKR"}]}