{"data":[{"stationId":"CKR","stationName":"CIKARANG","transitStation":false,"timeEst":743118660},{"transitStation":false,"timeEst":743118900,"stationName":"M.TELAGAMURNI","stationId":"TLM"},{"stationId":"CIT","transitStation":false,"stationName":"CIBITUNG","timeEst":743119020},{"stationId":"TB","stationName":"TAMBUN","transitStation":false,"timeEst":743119380},{"stationName":"BEKASITIMUR","timeEst":743119620,"transitStation":false,"stationId":"BKST"},{"timeEst":743119920,"transitStation":false,"stationId":"BKS","stationName":"BEKASI"},{"stationId":"KRI","stationName":"KRANJI","timeEst":743120100,"transitStation":false},{"stationName":"CAKUNG","stationId":"CUK","timeEst":743120400,"transitStation":false},{"timeEst":743120520,"stationId":"KLDB","stationName":"KLENDERBARU","transitStation":false},{"stationName":"BUARAN","timeEst":743120580,"stationId":"BUA","transitStation":false},{"timeEst":743120700,"stationId":"KLD","transitStation":false,"stationName":"KLENDER"},{"stationId":"JNG","timeEst":743121240,"transitStation":true,"stationName":"JATINEGARA"},{"transitStation":false,"timeEst":743121360,"stationId":"MTR","stationName":"MATRAMAN"},{"stationId":"MRI","transitStation":true,"timeEst":743121720,"stationName":"MANGGARAI"},{"stationName":"SUDIRMAN","stationId":"SUD","transitStation":false,"timeEst":743121960},{"stationId":"SUDB","stationName":"SUDIRMANBARU","timeEst":743122020,"transitStation":false},{"transitStation":false,"stationId":"KAT","stationName":"KARET","timeEst":743122080},{"stationName":"TANAHABANG","timeEst":743122380,"transitStation":true,"stationId":"THB"},{"timeEst":743122860,"stationName":"DURI","stationId":"DU","transitStation":true},{"timeEst":743123100,"transitStation":false,"stationId":"AK","stationName":"ANGKE"},{"transitStation":true,"stationId":"KPB","timeEst":743123580,"stationName":"KAMPUNGBANDAN"}]}