{"data":[{"timeEst":743129460,"stationId":"KPB","stationName":"KAMPUNGBANDAN","transitStation":true},{"stationId":"RJW","timeEst":743129640,"stationName":"RAJAWALI","transitStation":false},{"stationId":"KMO","transitStation":false,"stationName":"KEMAYORAN","timeEst":743129940},{"stationId":"GST","stationName":"GANGSENTIONG","timeEst":743130240,"transitStation":false},{"timeEst":743130300,"transitStation":false,"stationName":"KRAMAT","stationId":"KMT"},{"stationName":"PONDOKJATI","timeEst":743130420,"stationId":"POK","transitStation":false},{"transitStation":true,"stationId":"JNG","stationName":"JATINEGARA","timeEst":743130900},{"transitStation":false,"stationId":"KLD","timeEst":743131080,"stationName":"KLENDER"},{"transitStation":false,"stationId":"BUA","stationName":"BUARAN","timeEst":743131200},{"transitStation":false,"stationId":"KLDB","stationName":"KLENDERBARU","timeEst":743131260},{"transitStation":false,"stationId":"CUK","timeEst":743131740,"stationName":"CAKUNG"},{"stationId":"KRI","stationName":"KRANJI","transitStation":false,"timeEst":743131920},{"transitStation":false,"stationId":"BKS","stationName":"BEKASI","timeEst":743132160}]}