{"data":[{"transitStation":true,"timeEst":743163000,"stationName":"KAMPUNGBANDAN","stationId":"KPB"},{"transitStation":false,"timeEst":743163180,"stationId":"RJW","stationName":"RAJAWALI"},{"stationId":"KMO","timeEst":743163480,"stationName":"KEMAYORAN","transitStation":false},{"stationId":"GST","transitStation":false,"stationName":"GANGSENTIONG","timeEst":743163780},{"transitStation":false,"stationName":"KRAMAT","timeEst":743163840,"stationId":"KMT"},{"transitStation":false,"stationId":"POK","timeEst":743163960,"stationName":"PONDOKJATI"},{"stationId":"JNG","timeEst":743164740,"transitStation":true,"stationName":"JATINEGARA"},{"stationId":"KLD","timeEst":743164920,"stationName":"KLENDER","transitStation":false},{"stationId":"BUA","timeEst":743165040,"stationName":"BUARAN","transitStation":false},{"transitStation":false,"stationId":"KLDB","timeEst":743165100,"stationName":"KLENDERBARU"},{"stationId":"CUK","transitStation":false,"stationName":"CAKUNG","timeEst":743165580},{"timeEst":743165760,"transitStation":false,"stationName":"KRANJI","stationId":"KRI"},{"stationName":"BEKASI","timeEst":743166060,"transitStation":false,"stationId":"BKS"},{"stationId":"BKST","transitStation":false,"timeEst":743166180,"stationName":"BEKASITIMUR"},{"stationName":"TAMBUN","timeEst":743166600,"stationId":"TB","transitStation":false},{"stationName":"CIBITUNG","stationId":"CIT","transitStation":false,"timeEst":743166780},{"transitStation":false,"timeEst":743166900,"stationName":"M.TELAGAMURNI","stationId":"TLM"},{"stationId":"CKR","stationName":"CIKARANG","timeEst":743167260,"transitStation":false}]}