{"data":[{"stationId":"DU","timeEst":743143740,"stationName":"DURI","transitStation":true},{"stationId":"THB","stationName":"TANAHABANG","timeEst":743144160,"transitStation":true},{"stationName":"KARET","timeEst":743144340,"transitStation":false,"stationId":"KAT"},{"stationName":"SUDIRMANBARU","timeEst":743144520,"stationId":"SUDB","transitStation":false},{"stationName":"SUDIRMAN","transitStation":false,"stationId":"SUD","timeEst":743144580},{"transitStation":true,"timeEst":743144880,"stationName":"MANGGARAI","stationId":"MRI"}]}