{"data":[[{"is_transit":false,"i_long":106.790574,"time":0,"transit":false,"distance":0,"i_lat":-6.594596,"line":2,"station_id":"BOO","station_name":"Bogor"},{"i_lat":-6.530544,"line":2,"is_transit":false,"distance":7514,"station_name":"Cilebut","i_long":106.800016,"station_id":"CLT","time":9,"transit":false},{"transit":false,"distance":4331,"station_id":"BJD","line":2,"i_lat":-6.493243,"i_long":106.792719,"station_name":"Bojonggede","time":5,"is_transit":false},{"station_id":"CTA","i_long":106.800298,"is_transit":true,"i_lat":-6.448811,"time":5,"station_name":"Citayam","distance":5197,"transit":true,"line":2},{"station_name":"Pondok Rajeg","transit":false,"i_long":106.824374,"distance":0,"line":21,"station_id":"PDRG","is_transit":false,"time":0,"i_lat":-6.460735}]]}