{"data":[[{"i_lat":-7.801845,"time":0,"i_long":110.000548,"line":0,"transit":false,"is_transit":false,"station_name":"Jenar","station_id":"JN","distance":0},{"i_lat":-7.861626,"distance":8393,"time":10,"transit":false,"line":7,"station_name":"Wojo","station_id":"WJ","is_transit":false,"i_long":110.040449},{"station_name":"Wates","i_lat":-7.859237,"is_transit":false,"time":15,"line":7,"station_id":"WT","i_long":110.158003,"transit":false,"distance":13652},{"i_long":110.220122,"is_transit":false,"distance":10145,"station_id":"STL","i_lat":-7.832939,"time":25,"line":0,"transit":false,"station_name":"Sentolo"},{"distance":9041,"is_transit":false,"i_lat":-7.797702,"transit":false,"line":7,"time":8,"i_long":110.279205,"station_id":"RWL","station_name":"Rewulu"},{"transit":false,"station_id":"PTN","i_lat":-7.790605,"i_long":110.32542,"line":7,"distance":4579,"station_name":"Patukan","is_transit":false,"time":4},{"is_transit":false,"time":5,"station_name":"Yogyakarta","distance":4241,"station_id":"YK","i_long":110.36345,"transit":false,"line":7,"i_lat":-7.788961},{"distance":1307,"i_lat":-7.790018,"is_transit":false,"i_long":110.375434,"transit":false,"time":6,"line":7,"station_id":"LPN","station_name":"Lempuyangan"},{"time":7,"station_name":"Maguwo","line":7,"station_id":"MGW","distance":6799,"is_transit":false,"transit":false,"i_lat":-7.784476,"i_long":110.436791},{"station_id":"BBN","line":0,"distance":7905,"is_transit":false,"time":8,"station_name":"Brambanan","i_long":110.500451,"i_lat":-7.756284,"transit":false},{"transit":false,"time":7,"station_id":"SWT","is_transit":false,"station_name":"Srowot","distance":5850,"i_lat":-7.74111,"i_long":110.548972,"line":7},{"is_transit":false,"transit":false,"line":7,"distance":6738,"i_long":110.602981,"i_lat":-7.712087,"station_name":"Klaten","station_id":"KT","time":8},{"i_lat":-7.668597,"time":9,"station_name":"Ceper","transit":false,"is_transit":false,"line":7,"i_long":110.674861,"station_id":"CE","distance":9279},{"is_transit":false,"i_lat":-7.62181,"time":7,"distance":6271,"transit":false,"station_name":"Delanggu","i_long":110.706679,"line":7,"station_id":"DL"}]]}