{"data":[[{"is_transit":false,"distance":0,"transit":false,"i_long":106.74273,"line":6,"station_name":"Pondokranji","i_lat":-6.276362,"station_id":"PDJ","time":0},{"line":6,"transit":false,"i_lat":-6.288927,"is_transit":false,"station_name":"Jurangmangu","i_long":106.728916,"station_id":"JMU","time":3,"distance":2179},{"time":4,"distance":1994,"is_transit":false,"i_long":106.712277,"station_name":"Sudimara","station_id":"SDM","transit":false,"i_lat":-6.296963,"line":6},{"i_long":106.675475,"line":6,"station_name":"Rawa Buntu","transit":false,"station_id":"RU","distance":4566,"i_lat":-6.314823,"is_transit":false,"time":6},{"line":6,"i_lat":-6.319871,"distance":2413,"time":4,"i_long":106.66566,"station_name":"Serpong","transit":false,"station_id":"SRP","is_transit":false},{"time":4,"distance":1784,"station_name":"Cisauk","transit":false,"station_id":"CSK","i_long":106.640411,"i_lat":-6.32484,"line":3,"is_transit":false},{"i_long":106.617853,"distance":2519,"station_id":"CC","line":3,"station_name":"Cicayur","i_lat":-6.329547,"transit":false,"is_transit":false,"time":4},{"i_long":106.568863,"is_transit":false,"time":8,"distance":5968,"station_name":"Parung Panjang","line":6,"i_lat":-6.3441410000000005,"transit":false,"station_id":"PRP"},{"station_id":"CJT","station_name":"Cilejit","line":3,"is_transit":false,"time":9,"transit":false,"distance":7025,"i_lat":-6.354349,"i_long":106.508482},{"station_name":"Daru","i_long":106.491338,"i_lat":-6.338021,"transit":false,"station_id":"DAR","distance":2675,"line":0,"time":6,"is_transit":false},{"line":6,"station_name":"Tenjo","i_lat":-6.327251,"transit":false,"distance":3902,"station_id":"TEJ","i_long":106.460812,"is_transit":false,"time":5},{"transit":false,"is_transit":false,"distance":2974,"i_lat":-6.328533,"station_id":"TGS","station_name":"Tigaraksa","i_long":106.425991,"line":6,"time":5},{"time":3,"i_long":106.411216,"distance":2651,"line":3,"transit":false,"station_name":"Cikoya","station_id":"CKY","is_transit":false,"i_lat":-6.33561},{"station_id":"MJ","is_transit":false,"time":4,"i_lat":-6.332307,"station_name":"Maja","distance":1853,"i_long":106.394373,"transit":false,"line":6}]]}