{"data":[[{"station_id":"TLM","transit":false,"line":1,"distance":0,"i_long":107.093313,"is_transit":false,"i_lat":-6.262938,"station_name":"Metland Telaga Murni","time":0},{"is_transit":false,"station_id":"CIT","i_lat":-6.261877,"i_long":107.083084,"station_name":"Cibitung","transit":false,"time":2,"distance":2800,"line":1},{"transit":false,"station_id":"TB","station_name":"Tambun","time":3,"line":1,"i_lat":-6.258864,"i_long":107.055722,"distance":3420,"is_transit":false},{"is_transit":false,"time":7,"station_name":"Bekasi Timur","i_long":107.016735,"line":1,"transit":false,"i_lat":-6.248029,"distance":4460,"station_id":"BKST"},{"line":1,"time":2,"station_id":"BKS","i_lat":-6.236616,"transit":false,"distance":2368,"i_long":106.997013,"is_transit":false,"station_name":"Bekasi"},{"is_transit":false,"i_lat":-6.224515,"i_long":106.977657,"station_name":"Kranji","transit":false,"station_id":"KRI","time":4,"line":1,"distance":2520}]]}