{"data":[[{"line":5,"station_id":"TTI","time":0,"distance":0,"transit":false,"station_name":"Tanah Tinggi","i_long":106.64657,"is_transit":false,"i_lat":-6.17331},{"distance":2028,"i_long":106.665036,"line":5,"time":3,"station_name":"Batuceper","transit":false,"is_transit":false,"i_lat":-6.171811,"station_id":"BPR"},{"transit":false,"station_id":"PI","distance":1834,"time":3,"station_name":"Poris","is_transit":false,"i_lat":-6.169933,"line":5,"i_long":106.679458},{"is_transit":false,"time":3,"transit":false,"distance":2548,"station_id":"KDS","i_long":106.701612,"station_name":"Kalideres","line":5,"i_lat":-6.166068},{"station_id":"RW","distance":2504,"station_name":"Rawa Buaya","line":5,"transit":false,"is_transit":false,"i_lat":-6.162758,"time":3,"i_long":106.723064},{"transit":false,"station_id":"BOI","i_long":106.737035,"i_lat":-6.159876,"station_name":"Bojongindah","time":4,"distance":1152,"is_transit":false,"line":5},{"line":5,"is_transit":false,"transit":false,"time":2,"station_id":"TKO","distance":2334,"station_name":"Taman Kota","i_long":106.756522,"i_lat":-6.1587309999999995},{"transit":false,"time":2,"station_name":"Pesing","distance":1614,"i_lat":-6.161433,"line":5,"station_id":"PSG","is_transit":false,"i_long":106.771379},{"line":5,"i_lat":-6.162021,"i_long":106.788277,"is_transit":false,"transit":false,"station_name":"Grogol","station_id":"GGL","time":2,"distance":2036},{"distance":1700,"is_transit":true,"station_name":"Duri","station_id":"DU","line":1,"i_long":106.800832,"time":3,"i_lat":-6.155215,"transit":true},{"station_name":"Tanah Abang","is_transit":false,"station_id":"THB","time":8,"transit":false,"line":1,"i_lat":-6.185545,"distance":3632,"i_long":106.811091},{"i_long":106.816351,"is_transit":false,"distance":2029,"i_lat":-6.20132,"line":1,"time":5,"transit":false,"station_id":"KAT","station_name":"Karet"},{"transit":false,"station_id":"SUDB","distance":471,"line":1,"station_name":"Sudirman Baru","time":1,"is_transit":false,"i_lat":-6.201433,"i_long":106.819881},{"i_long":106.822649,"transit":false,"is_transit":false,"time":1,"station_id":"SUD","line":1,"station_name":"Sudirman","i_lat":-6.202263,"distance":280},{"is_transit":true,"distance":3186,"line":2,"station_id":"MRI","time":4,"transit":true,"i_long":106.84912,"station_name":"Manggarai","i_lat":-6.209883},{"station_name":"Tebet","i_long":106.857948,"time":4,"distance":2610,"transit":false,"station_id":"TEB","line":2,"i_lat":-6.226659,"is_transit":false},{"i_long":106.856607,"line":2,"station_id":"CW","i_lat":-6.242512,"transit":false,"is_transit":false,"distance":1230,"time":2,"station_name":"Cawang"},{"distance":1546,"station_name":"Duren Kalibata","is_transit":false,"i_lat":-6.255332,"i_long":106.85449,"line":2,"transit":false,"station_id":"DRN","time":3}],[{"i_long":106.64657,"transit":false,"station_id":"TTI","station_name":"Tanah Tinggi","i_lat":-6.17331,"time":0,"is_transit":false,"distance":0,"line":5},{"time":3,"distance":2028,"station_id":"BPR","is_transit":false,"transit":false,"i_lat":-6.171811,"line":5,"station_name":"Batuceper","i_long":106.665036},{"line":5,"distance":1834,"transit":false,"station_name":"Poris","time":3,"station_id":"PI","i_long":106.679458,"is_transit":false,"i_lat":-6.169933},{"i_lat":-6.166068,"transit":false,"station_name":"Kalideres","time":3,"distance":2548,"station_id":"KDS","is_transit":false,"line":5,"i_long":106.701612},{"time":3,"distance":2504,"i_long":106.723064,"line":5,"is_transit":false,"station_name":"Rawa Buaya","station_id":"RW","i_lat":-6.162758,"transit":false},{"i_lat":-6.159876,"time":4,"is_transit":false,"station_id":"BOI","i_long":106.737035,"distance":1152,"transit":false,"line":5,"station_name":"Bojongindah"},{"transit":false,"station_id":"TKO","time":2,"i_long":106.756522,"i_lat":-6.1587309999999995,"line":5,"station_name":"Taman Kota","is_transit":false,"distance":2334},{"time":2,"is_transit":false,"transit":false,"station_id":"PSG","station_name":"Pesing","line":5,"i_lat":-6.161433,"i_long":106.771379,"distance":1614},{"distance":2036,"i_lat":-6.162021,"station_name":"Grogol","line":5,"station_id":"GGL","i_long":106.788277,"time":2,"transit":false,"is_transit":false},{"i_lat":-6.155215,"station_id":"DU","transit":true,"station_name":"Duri","is_transit":true,"i_long":106.800832,"line":1,"time":3,"distance":1700},{"time":4,"station_name":"Angke","station_id":"AK","is_transit":false,"i_long":106.79867,"transit":false,"line":1,"i_lat":-6.144674,"distance":1230},{"i_long":106.826365,"transit":true,"station_id":"KPB","station_name":"Kampung Bandan","distance":4102,"is_transit":true,"i_lat":-6.132549,"line":4,"time":9},{"line":2,"is_transit":true,"distance":1364,"station_id":"JAKK","station_name":"Jakarta Kota","i_lat":-6.137569,"i_long":106.812439,"transit":true,"time":3},{"station_name":"Jayakarta","transit":false,"time":4,"i_lat":-6.141205,"station_id":"JAY","line":2,"distance":1264,"is_transit":false,"i_long":106.820901},{"time":2,"line":2,"station_name":"Manggabesar","transit":false,"station_id":"MGB","i_lat":-6.149769,"i_long":106.82482,"is_transit":false,"distance":1080},{"i_long":106.827103,"time":2,"station_name":"Sawah Besar","line":2,"transit":false,"i_lat":-6.160725,"distance":906,"is_transit":false,"station_id":"SW"},{"line":2,"time":2,"distance":1149,"i_lat":-6.166716,"is_transit":false,"station_id":"JUA","transit":false,"i_long":106.828284,"station_name":"Juanda"},{"line":2,"station_name":"Gondangdia","station_id":"GDD","time":4,"transit":false,"is_transit":false,"i_long":106.832183,"distance":2015,"i_lat":-6.186295},{"station_id":"CKI","i_lat":-6.198556,"i_long":106.840169,"station_name":"Cikini","line":2,"is_transit":false,"transit":false,"time":3,"distance":1750},{"transit":false,"time":4,"distance":1590,"is_transit":false,"station_id":"MRI","station_name":"Manggarai","i_lat":-6.209883,"i_long":106.84912,"line":2},{"time":4,"is_transit":false,"i_long":106.857948,"i_lat":-6.226659,"station_name":"Tebet","station_id":"TEB","line":2,"transit":false,"distance":2610},{"transit":false,"time":2,"station_id":"CW","is_transit":false,"station_name":"Cawang","line":2,"distance":1230,"i_long":106.856607,"i_lat":-6.242512},{"i_long":106.85449,"is_transit":false,"station_id":"DRN","distance":1546,"station_name":"Duren Kalibata","line":2,"time":3,"i_lat":-6.255332,"transit":false}],[{"time":0,"transit":false,"station_name":"Tanah Tinggi","is_transit":false,"distance":0,"station_id":"TTI","line":5,"i_lat":-6.17331,"i_long":106.64657},{"transit":false,"is_transit":false,"distance":2028,"station_name":"Batuceper","i_lat":-6.171811,"i_long":106.665036,"time":3,"line":5,"station_id":"BPR"},{"station_id":"PI","time":3,"line":5,"is_transit":false,"transit":false,"distance":1834,"station_name":"Poris","i_lat":-6.169933,"i_long":106.679458},{"i_long":106.701612,"transit":false,"is_transit":false,"i_lat":-6.166068,"station_name":"Kalideres","distance":2548,"station_id":"KDS","line":5,"time":3},{"station_name":"Rawa Buaya","line":5,"is_transit":false,"transit":false,"station_id":"RW","i_lat":-6.162758,"time":3,"distance":2504,"i_long":106.723064},{"time":4,"station_name":"Bojongindah","transit":false,"i_long":106.737035,"line":5,"is_transit":false,"station_id":"BOI","i_lat":-6.159876,"distance":1152},{"time":2,"is_transit":false,"transit":false,"station_id":"TKO","i_long":106.756522,"station_name":"Taman Kota","distance":2334,"i_lat":-6.1587309999999995,"line":5},{"station_name":"Pesing","i_long":106.771379,"time":2,"transit":false,"distance":1614,"is_transit":false,"station_id":"PSG","i_lat":-6.161433,"line":5},{"i_lat":-6.162021,"distance":2036,"station_id":"GGL","i_long":106.788277,"line":5,"station_name":"Grogol","time":2,"is_transit":false,"transit":false},{"station_id":"DU","is_transit":true,"i_lat":-6.155215,"i_long":106.800832,"station_name":"Duri","transit":true,"time":3,"distance":1700,"line":1},{"station_name":"Angke","is_transit":false,"line":1,"i_long":106.79867,"time":4,"i_lat":-6.144674,"station_id":"AK","transit":false,"distance":1230},{"time":9,"is_transit":true,"line":4,"station_name":"Kampung Bandan","station_id":"KPB","i_lat":-6.132549,"distance":4102,"i_long":106.826365,"transit":true},{"i_lat":-6.14505,"transit":false,"time":3,"station_id":"RJW","i_long":106.836569,"line":11,"is_transit":false,"distance":1444,"station_name":"Rajawali"},{"is_transit":false,"line":11,"transit":false,"time":5,"station_name":"Kemayoran","distance":1901,"station_id":"KMO","i_lat":-6.161728,"i_long":106.839204},{"line":11,"transit":false,"i_long":106.84368,"time":4,"distance":1436,"station_id":"PSE","station_name":"Pasar Senen","is_transit":false,"i_lat":-6.174784},{"transit":false,"station_name":"Gang Sentiong","time":8,"distance":1567,"station_id":"GST","i_lat":-6.185975,"i_long":106.850107,"is_transit":false,"line":11},{"station_id":"KMT","distance":973,"is_transit":false,"station_name":"Kramat","i_long":106.855437,"transit":false,"i_lat":-6.193792,"time":1,"line":11},{"station_name":"Pondok Jati","is_transit":false,"line":11,"i_long":106.861737,"transit":false,"time":2,"distance":1829,"i_lat":-6.209188,"station_id":"POK"},{"line":1,"time":9,"is_transit":true,"i_long":106.86807400000001,"i_lat":-6.215091,"distance":1236,"station_id":"JNG","transit":true,"station_name":"Jatinegara"},{"is_transit":false,"i_lat":-6.212485,"transit":false,"station_name":"Matraman","time":2,"i_long":106.858896,"distance":1377,"line":1,"station_id":"MTR"},{"is_transit":true,"line":2,"time":2,"station_id":"MRI","station_name":"Manggarai","transit":true,"i_lat":-6.209883,"i_long":106.84912,"distance":1275},{"time":4,"line":2,"is_transit":false,"i_long":106.857948,"transit":false,"station_id":"TEB","i_lat":-6.226659,"station_name":"Tebet","distance":2610},{"i_lat":-6.242512,"distance":1230,"i_long":106.856607,"transit":false,"station_name":"Cawang","time":2,"station_id":"CW","is_transit":false,"line":2},{"transit":false,"i_lat":-6.255332,"line":2,"i_long":106.85449,"is_transit":false,"distance":1546,"station_id":"DRN","time":3,"station_name":"Duren Kalibata"}]]}